cfm_package/__init__.py
cfm_package/__main__.py
cfm_package/cfm_mcp_server.py
cfm_package/cli.py
cfm_package/main.py
cfm_package/py.typed
context_file_manager-0.5.4.dist-info/licenses/LICENSE
context_file_manager-0.5.4.dist-info/METADATA
context_file_manager-0.5.4.dist-info/WHEEL
context_file_manager-0.5.4.dist-info/entry_points.txt
context_file_manager-0.5.4.dist-info/top_level.txt
context_file_manager-0.5.4.dist-info/RECORD
