Metadata-Version: 2.4
Name: context-file-manager
Version: 0.5.4
Summary: A CLI tool for managing shared context files across projects
Home-page: https://github.com/ananddtyagi/context-file-manager
Author: Anand Tyagi
Author-email: Anand Tyagi <anand.deep.tyagi@gmail.com>
Project-URL: Homepage, https://github.com/ananddtyagi/context-file-manager
Project-URL: Bug Tracker, https://github.com/ananddtyagi/context-file-manager/issues
Project-URL: Source, https://github.com/ananddtyagi/context-file-manager
Keywords: file management,context files,cli tool,project management
Classifier: Development Status :: 3 - Alpha
Classifier: Intended Audience :: Developers
Classifier: Topic :: Software Development :: Libraries :: Python Modules
Classifier: Topic :: System :: Filesystems
Classifier: License :: OSI Approved :: MIT License
Classifier: Programming Language :: Python :: 3
Classifier: Programming Language :: Python :: 3.7
Classifier: Programming Language :: Python :: 3.8
Classifier: Programming Language :: Python :: 3.9
Classifier: Programming Language :: Python :: 3.10
Classifier: Programming Language :: Python :: 3.11
Classifier: Programming Language :: Python :: 3.12
Classifier: Operating System :: OS Independent
Requires-Python: >=3.7
License-File: LICENSE
Provides-Extra: mcp
Requires-Dist: mcp>=1.0.0; extra == "mcp"
Provides-Extra: all
Requires-Dist: mcp>=1.0.0; extra == "all"
Dynamic: author
Dynamic: home-page
Dynamic: license-file
Dynamic: requires-python
